mh_universal_functions/__init__.py
mh_universal_functions/_version.py
mh_universal_functions/mh_universal_functions.py
mh_universal_functions-2022.4.9.1.dist-info/LICENSE
mh_universal_functions-2022.4.9.1.dist-info/METADATA
mh_universal_functions-2022.4.9.1.dist-info/WHEEL
mh_universal_functions-2022.4.9.1.dist-info/top_level.txt
mh_universal_functions-2022.4.9.1.dist-info/RECORD
