Metadata-Version: 2.1
Name: mh-universal-functions
Version: 2022.4.9.1
Summary: General functions library
Home-page: https://pypi.org/project/mh-universal-functions
Author: MH
Author-email: ibhmduu1721nhg11.11@o2mail.de
License: MIT
Platform: UNKNOWN
Classifier: Programming Language :: Python :: 3
Classifier: License :: OSI Approved :: MIT License
Classifier: Operating System :: OS Independent
Requires-Python: >=3.7
